FanyiMantanZenyangFanyiGengDidao/README.md
FanyiMantanZenyangFanyiGengDidao/__init__.py
FanyiMantanZenyangFanyiGengDidao/__main__.py
FanyiMantanZenyangFanyiGengDidao/file.epub
FanyiMantanZenyangFanyiGengDidao/index.html
FanyiMantanZenyangFanyiGengDidao/css/__init__.py
FanyiMantanZenyangFanyiGengDidao/css/annotations.css
FanyiMantanZenyangFanyiGengDidao/css/main.css
FanyiMantanZenyangFanyiGengDidao/css/normalize.css
FanyiMantanZenyangFanyiGengDidao/css/popup.css
FanyiMantanZenyangFanyiGengDidao/font/__init__.py
FanyiMantanZenyangFanyiGengDidao/font/fontello.eot
FanyiMantanZenyangFanyiGengDidao/font/fontello.svg
FanyiMantanZenyangFanyiGengDidao/font/fontello.ttf
FanyiMantanZenyangFanyiGengDidao/font/fontello.woff
FanyiMantanZenyangFanyiGengDidao/img/__init__.py
FanyiMantanZenyangFanyiGengDidao/img/annotator-glyph-sprite.png
FanyiMantanZenyangFanyiGengDidao/img/annotator-icon-sprite.png
FanyiMantanZenyangFanyiGengDidao/img/apple-touch-icon.png
FanyiMantanZenyangFanyiGengDidao/img/cancelfullscreen.png
FanyiMantanZenyangFanyiGengDidao/img/close.png
FanyiMantanZenyangFanyiGengDidao/img/fullscreen.png
FanyiMantanZenyangFanyiGengDidao/img/loader.gif
FanyiMantanZenyangFanyiGengDidao/img/menu-icon.png
FanyiMantanZenyangFanyiGengDidao/img/save.png
FanyiMantanZenyangFanyiGengDidao/img/saved.png
FanyiMantanZenyangFanyiGengDidao/img/settings-s.png
FanyiMantanZenyangFanyiGengDidao/img/settings.png
FanyiMantanZenyangFanyiGengDidao/img/star.png
FanyiMantanZenyangFanyiGengDidao/js/__init__.py
FanyiMantanZenyangFanyiGengDidao/js/epub.js
FanyiMantanZenyangFanyiGengDidao/js/epub.min.js
FanyiMantanZenyangFanyiGengDidao/js/epub.min.map
FanyiMantanZenyangFanyiGengDidao/js/hooks.min.js
FanyiMantanZenyangFanyiGengDidao/js/hooks.min.map
FanyiMantanZenyangFanyiGengDidao/js/reader.js
FanyiMantanZenyangFanyiGengDidao/js/reader.js.map
FanyiMantanZenyangFanyiGengDidao/js/reader.min.js
FanyiMantanZenyangFanyiGengDidao/js/reader.min.map
FanyiMantanZenyangFanyiGengDidao/js/hooks/__init__.py
fanyi_mantan_zenyang_fanyi_geng_didao-2024.3.1.0.dist-info/METADATA
fanyi_mantan_zenyang_fanyi_geng_didao-2024.3.1.0.dist-info/WHEEL
fanyi_mantan_zenyang_fanyi_geng_didao-2024.3.1.0.dist-info/entry_points.txt
fanyi_mantan_zenyang_fanyi_geng_didao-2024.3.1.0.dist-info/top_level.txt
fanyi_mantan_zenyang_fanyi_geng_didao-2024.3.1.0.dist-info/RECORD
